Metadata-Version: 2.1
Name: maytak
Version: 0.0
Summary: Data Science OCR
Author-email: maytak.roman@mail.ru
